dqt/dqt.py
dqt/sql/templates/macros/macros.jinja
dqt_lyst-0.1.0.dist-info/METADATA
dqt_lyst-0.1.0.dist-info/WHEEL
dqt_lyst-0.1.0.dist-info/RECORD
