Metadata-Version: 2.1
Name: dqt-lyst
Version: 0.1.0
Summary: 
Author: Mark Ingham
Author-email: mark.ingham@ly.st
Requires-Python: >=3.11,<3.13
Classifier: Programming Language :: Python :: 3
Classifier: Programming Language :: Python :: 3.11
Requires-Dist: decouple (>=0.0.7,<0.0.8)
Requires-Dist: duckdb (>=0.9.1,<0.10.0)
Requires-Dist: jinja2 (>=3.1.2,<4.0.0)
Requires-Dist: numpy (>=1.26.1,<2.0.0)
Requires-Dist: pandas (>=2.1.1,<3.0.0)
Requires-Dist: pytest (>=7.4.2,<8.0.0)
Requires-Dist: python-decouple (>=3.8,<4.0)
Requires-Dist: python-dotenv (>=1.0.0,<2.0.0)
Requires-Dist: snowflake-connector-python (>=3.3.1,<4.0.0)
Requires-Dist: sqlparse (>=0.4.4,<0.5.0)
